puma/__init__.py
puma-0.0.0rc1.dist-info/METADATA
puma-0.0.0rc1.dist-info/WHEEL
puma-0.0.0rc1.dist-info/top_level.txt
puma-0.0.0rc1.dist-info/RECORD
