Metadata-Version: 2.1
Name: puma
Version: 0.0.0rc1
Summary: Python Unified Multi-tasking API (PUMA)
Home-page: https://github.com/gift-surg/puma
Author: GIFT-Surg Consortium
License: UNKNOWN
Platform: UNKNOWN
